[{"DATETIME":1714060901516,"ACAO":"CRIACAO","DADO":[{"nome":"Marcelinho","idade":"22","genero":"Feminino"}]},{"DATETIME":1714061271660,"ACAO":"LEITURA","DADO":""},{"DATETIME":1714061274962,"ACAO":"LEITURA","DADO":""},{"DATETIME":1714061294366,"ACAO":"LEITURA","DADO":""},{"DATETIME":1714061294373,"ACAO":"CRIACAO","DADO":[{"nome":"Carlos","idade":"12","genero":"Feminino"}]},{"DATETIME":1714061296538,"ACAO":"LEITURA","DADO":""},{"DATETIME":1714061298482,"ACAO":"LEITURA","DADO":""},{"DATETIME":1714061303443,"ACAO":"ATUALIZACAO","DADO":[{"nome":"Richard Ochoa","idade":66,"genero":"Masculino"},{"nome":"Kaitlyn Nguyen","idade":31,"genero":"Masculino"},{"nome":"Karl Hicks","idade":57,"genero":"Feminino"},{"nome":"Juan Schwartz","idade":26,"genero":"Feminino"},{"nome":"Eric Friedman","idade":80,"genero":"Feminino"},{"nome":"Kimberly Lee DVM","idade":35,"genero":"Feminino"},{"nome":"Lisa Clements","idade":26,"genero":"Masculino"},{"nome":"Heidi Phillips","idade":52,"genero":"Masculino"},{"nome":"James Zimmerman","idade":65,"genero":"Feminino"},{"nome":"Nancy Munoz","idade":79,"genero":"Masculino"},{"nome":"Margaret Hall","idade":73,"genero":"Feminino"},{"nome":"Carlos Villanueva","idade":30,"genero":"Masculino"},{"nome":"Donald Davis","idade":45,"genero":"Masculino"},{"nome":"Benjamin Miller","idade":34,"genero":"Masculino"},{"nome":"Rhonda Hernandez","idade":79,"genero":"Masculino"},{"nome":"Joanna Callahan","idade":40,"genero":"Masculino"},{"nome":"David Johnson","idade":53,"genero":"Masculino"},{"nome":"Lauren Woodward MD","idade":21,"genero":"Feminino"},{"nome":"Carl York","idade":26,"genero":"Masculino"},{"nome":"Kathryn Carrillo","idade":60,"genero":"Masculino"},{"nome":"Jacob Cannon","idade":48,"genero":"Masculino"},{"nome":"Antonio Sanchez","idade":62,"genero":"Masculino"},{"nome":"Lisa Atkinson","idade":41,"genero":"Masculino"},{"nome":"Kristina Gilmore","idade":78,"genero":"Masculino"},{"nome":"Lisa Simpson","idade":54,"genero":"Feminino"},{"nome":"Jonathan Myers","idade":36,"genero":"Masculino"},{"nome":"Tyler Costa","idade":42,"genero":"Feminino"},{"nome":"Susan Lin","idade":33,"genero":"Feminino"},{"nome":"Stephanie Gardner","idade":21,"genero":"Feminino"},{"nome":"Megan Hughes","idade":48,"genero":"Masculino"},{"nome":"Andrea Proctor","idade":73,"genero":"Feminino"},{"nome":"Kimberly Blair","idade":48,"genero":"Masculino"},{"nome":"Joanna James","idade":68,"genero":"Feminino"},{"nome":"Kelly Riddle","idade":45,"genero":"Masculino"},{"nome":"Ashley West","idade":38,"genero":"Masculino"},{"nome":"Dr. Emily Mitchell","idade":34,"genero":"Feminino"},{"nome":"Jessica Smith","idade":55,"genero":"Feminino"},{"nome":"William Gomez","idade":72,"genero":"Feminino"},{"nome":"Sharon Brown","idade":26,"genero":"Feminino"},{"nome":"Aimee Young","idade":44,"genero":"Feminino"},{"nome":"Lindsay Fry","idade":53,"genero":"Masculino"},{"nome":"Joann Perkins","idade":62,"genero":"Masculino"},{"nome":"Tammy Davis","idade":34,"genero":"Masculino"},{"nome":"Michelle Solomon","idade":57,"genero":"Feminino"},{"nome":"Eric Shaw","idade":68,"genero":"Feminino"},{"nome":"Rita Davis","idade":68,"genero":"Masculino"},{"nome":"Nicholas Dawson","idade":51,"genero":"Masculino"},{"nome":"Sarah Davis","idade":26,"genero":"Feminino"},{"nome":"Keith Guzman","idade":22,"genero":"Masculino"},{"nome":"Dwayne Melendez","idade":35,"genero":"Feminino"},{"nome":"Marcelo","idade":12,"genero":"Feminino"},{"nome":"Marcelinho","idade":22,"genero":"Feminino"},{"nome":"Carlos G","idade":12,"genero":"Feminino"}]},{"DATETIME":1714061304931,"ACAO":"LEITURA","DADO":""},{"DATETIME":1714061308430,"ACAO":"LEITURA","DADO":""},{"DATETIME":1714061310743,"ACAO":"DELECAO","DADO":[{"nome":"Richard Ochoa","idade":66,"genero":"Masculino"},{"nome":"Kaitlyn Nguyen","idade":31,"genero":"Masculino"},{"nome":"Karl Hicks","idade":57,"genero":"Feminino"},{"nome":"Juan Schwartz","idade":26,"genero":"Feminino"},{"nome":"Eric Friedman","idade":80,"genero":"Feminino"},{"nome":"Kimberly Lee DVM","idade":35,"genero":"Feminino"},{"nome":"Lisa Clements","idade":26,"genero":"Masculino"},{"nome":"Heidi Phillips","idade":52,"genero":"Masculino"},{"nome":"James Zimmerman","idade":65,"genero":"Feminino"},{"nome":"Nancy Munoz","idade":79,"genero":"Masculino"},{"nome":"Margaret Hall","idade":73,"genero":"Feminino"},{"nome":"Carlos Villanueva","idade":30,"genero":"Masculino"},{"nome":"Donald Davis","idade":45,"genero":"Masculino"},{"nome":"Benjamin Miller","idade":34,"genero":"Masculino"},{"nome":"Rhonda Hernandez","idade":79,"genero":"Masculino"},{"nome":"Joanna Callahan","idade":40,"genero":"Masculino"},{"nome":"David Johnson","idade":53,"genero":"Masculino"},{"nome":"Lauren Woodward MD","idade":21,"genero":"Feminino"},{"nome":"Carl York","idade":26,"genero":"Masculino"},{"nome":"Kathryn Carrillo","idade":60,"genero":"Masculino"},{"nome":"Jacob Cannon","idade":48,"genero":"Masculino"},{"nome":"Antonio Sanchez","idade":62,"genero":"Masculino"},{"nome":"Lisa Atkinson","idade":41,"genero":"Masculino"},{"nome":"Kristina Gilmore","idade":78,"genero":"Masculino"},{"nome":"Lisa Simpson","idade":54,"genero":"Feminino"},{"nome":"Jonathan Myers","idade":36,"genero":"Masculino"},{"nome":"Tyler Costa","idade":42,"genero":"Feminino"},{"nome":"Susan Lin","idade":33,"genero":"Feminino"},{"nome":"Stephanie Gardner","idade":21,"genero":"Feminino"},{"nome":"Megan Hughes","idade":48,"genero":"Masculino"},{"nome":"Andrea Proctor","idade":73,"genero":"Feminino"},{"nome":"Kimberly Blair","idade":48,"genero":"Masculino"},{"nome":"Joanna James","idade":68,"genero":"Feminino"},{"nome":"Kelly Riddle","idade":45,"genero":"Masculino"},{"nome":"Ashley West","idade":38,"genero":"Masculino"},{"nome":"Dr. Emily Mitchell","idade":34,"genero":"Feminino"},{"nome":"Jessica Smith","idade":55,"genero":"Feminino"},{"nome":"William Gomez","idade":72,"genero":"Feminino"},{"nome":"Sharon Brown","idade":26,"genero":"Feminino"},{"nome":"Aimee Young","idade":44,"genero":"Feminino"},{"nome":"Lindsay Fry","idade":53,"genero":"Masculino"},{"nome":"Joann Perkins","idade":62,"genero":"Masculino"},{"nome":"Tammy Davis","idade":34,"genero":"Masculino"},{"nome":"Michelle Solomon","idade":57,"genero":"Feminino"},{"nome":"Eric Shaw","idade":68,"genero":"Feminino"},{"nome":"Rita Davis","idade":68,"genero":"Masculino"},{"nome":"Nicholas Dawson","idade":51,"genero":"Masculino"},{"nome":"Sarah Davis","idade":26,"genero":"Feminino"},{"nome":"Keith Guzman","idade":22,"genero":"Masculino"},{"nome":"Dwayne Melendez","idade":35,"genero":"Feminino"},{"nome":"Marcelo","idade":12,"genero":"Feminino"},{"nome":"Marcelinho","idade":22,"genero":"Feminino"}]},{"DATETIME":1714061313722,"ACAO":"LEITURA","DADO":""},{"DATETIME":1714061719936,"ACAO":"LEITURA","DADO":""},{"DATETIME":1714061719945,"ACAO":"CRIACAO","DADO":[{"nome":"Gabriel","idade":"13","genero":"Feminino"}]},{"DATETIME":1714061723631,"ACAO":"LEITURA","DADO":""},{"DATETIME":1714061799110,"ACAO":"LEITURA","DADO":""},{"DATETIME":1714061804663,"ACAO":"ATUALIZACAO","DADO":["Gabriel G",13,"Feminino"]},{"DATETIME":1714061808372,"ACAO":"LEITURA","DADO":""},{"DATETIME":1714061886739,"ACAO":"LEITURA","DADO":""},{"DATETIME":1714061894918,"ACAO":"LEITURA","DADO":""},{"DATETIME":1714061906982,"ACAO":"LEITURA","DADO":""},{"DATETIME":1714061931423,"ACAO":"LEITURA","DADO":""},{"DATETIME":1714061932756,"ACAO":"LEITURA","DADO":""},{"DATETIME":1714061939700,"ACAO":"LEITURA","DADO":""},{"DATETIME":1714061944092,"ACAO":"LEITURA","DADO":""},{"DATETIME":1714061949177,"ACAO":"DELECAO","DADO":["Keith Guzman","13\/01\/2024",[{"nome":"Endoscopia"},{"nome":"Colonoscopia"}]]},{"DATETIME":1714061956700,"ACAO":"LEITURA","DADO":""},{"DATETIME":1714061965502,"ACAO":"LEITURA","DADO":""},{"DATETIME":1714061965526,"ACAO":"CRIACAO","DADO":[{"nome":"Marcelo","data":"120-102","procedimentos":[]}]},{"DATETIME":1714061994307,"ACAO":"LEITURA","DADO":""},{"DATETIME":1714062003165,"ACAO":"LEITURA","DADO":""},{"DATETIME":1714062006115,"ACAO":"LEITURA","DADO":""},{"DATETIME":1714062073207,"ACAO":"LEITURA","DADO":""},{"DATETIME":1714062087258,"ACAO":"LEITURA","DADO":""},{"DATETIME":1714062091952,"ACAO":"LEITURA","DADO":""},{"DATETIME":1714062091962,"ACAO":"ATUALIZACAO","DADO":["Gabriel G","11\/01\/2024",[{"nome":"Colonoscopia"}]]},{"DATETIME":1714062097098,"ACAO":"LEITURA","DADO":""},{"DATETIME":1714062800216,"ACAO":"LEITURA","DADO":""},{"DATETIME":1714062806918,"ACAO":"LEITURA","DADO":""},{"DATETIME":1714062813312,"ACAO":"LEITURA","DADO":""},{"DATETIME":1714062819309,"ACAO":"LEITURA","DADO":""},{"DATETIME":1714062819321,"ACAO":"CRIACAO","DADO":[{"nome":"Marcelo","data":"1203","procedimentos":[{"nome":"Raio-X"}]}]},{"DATETIME":1714062873961,"ACAO":"LEITURA","DADO":""},{"DATETIME":1714062876475,"ACAO":"LEITURA","DADO":""},{"DATETIME":1714062880615,"ACAO":"LEITURA","DADO":""},{"DATETIME":1714063057197,"ACAO":"LEITURA","DADO":""},{"DATETIME":1714063062417,"ACAO":"LEITURA","DADO":""},{"DATETIME":1714063064272,"ACAO":"LEITURA","DADO":""},{"DATETIME":1714063068258,"ACAO":"LEITURA","DADO":""},{"DATETIME":1714063072663,"ACAO":"LEITURA","DADO":""},{"DATETIME":1714063198341,"ACAO":"LEITURA","DADO":""},{"DATETIME":1714063202477,"ACAO":"LEITURA","DADO":""},{"DATETIME":1714063205865,"ACAO":"LEITURA","DADO":""},{"DATETIME":1714063208005,"ACAO":"LEITURA","DADO":""},{"DATETIME":1714063210420,"ACAO":"LEITURA","DADO":""},{"DATETIME":1714063279261,"ACAO":"LEITURA","DADO":""},{"DATETIME":1714063280850,"ACAO":"LEITURA","DADO":""},{"DATETIME":1714063282971,"ACAO":"LEITURA","DADO":""},{"DATETIME":1714063314633,"ACAO":"LEITURA","DADO":""},{"DATETIME":1714063316164,"ACAO":"DELECAO","DADO":["Marcelo",12,"Feminino"]},{"DATETIME":1714063318383,"ACAO":"LEITURA","DADO":""},{"DATETIME":1714063350266,"ACAO":"LEITURA","DADO":""},{"DATETIME":1714063452228,"ACAO":"LEITURA","DADO":""},{"DATETIME":1714063454481,"ACAO":"LEITURA","DADO":""},{"DATETIME":1714063506053,"ACAO":"LEITURA","DADO":""},{"DATETIME":1714063508208,"ACAO":"DELECAO","DADO":["Marcelo",22,"Masculino"]},{"DATETIME":1714063511074,"ACAO":"LEITURA","DADO":""},{"DATETIME":1714063600259,"ACAO":"LEITURA","DADO":""},{"DATETIME":1714063605278,"ACAO":"LEITURA","DADO":""},{"DATETIME":1714063608434,"ACAO":"LEITURA","DADO":""},{"DATETIME":1714063613312,"ACAO":"LEITURA","DADO":""},{"DATETIME":1714063617051,"ACAO":"LEITURA","DADO":""},{"DATETIME":1714063698785,"ACAO":"LEITURA","DADO":""},{"DATETIME":1714063701640,"ACAO":"LEITURA","DADO":""},{"DATETIME":1714063705736,"ACAO":"LEITURA","DADO":""},{"DATETIME":1714063719589,"ACAO":"LEITURA","DADO":""},{"DATETIME":1714063728260,"ACAO":"LEITURA","DADO":""},{"DATETIME":1714063961103,"ACAO":"LEITURA","DADO":""},{"DATETIME":1714063964060,"ACAO":"LEITURA","DADO":""},{"DATETIME":1714063967557,"ACAO":"LEITURA","DADO":""},{"DATETIME":1714064005166,"ACAO":"LEITURA","DADO":""},{"DATETIME":1714064009852,"ACAO":"LEITURA","DADO":""},{"DATETIME":1714064015003,"ACAO":"LEITURA","DADO":""},{"DATETIME":1714064018148,"ACAO":"LEITURA","DADO":""},{"DATETIME":1714064122178,"ACAO":"LEITURA","DADO":""},{"DATETIME":1714064131179,"ACAO":"LEITURA","DADO":""},{"DATETIME":1714064152758,"ACAO":"LEITURA","DADO":""},{"DATETIME":1714064154530,"ACAO":"DELECAO","DADO":["Marcelo",22,"Masculino"]},{"DATETIME":1714064224837,"ACAO":"LEITURA","DADO":""},{"DATETIME":1714064226432,"ACAO":"DELECAO","DADO":["Marcelo",22,"Masculino"]},{"DATETIME":1714064322748,"ACAO":"LEITURA","DADO":""},{"DATETIME":1714064324818,"ACAO":"DELECAO","DADO":["Marcelo",22,"Masculino"]},{"DATETIME":1714064363732,"ACAO":"LEITURA","DADO":""},{"DATETIME":1714064365709,"ACAO":"DELECAO","DADO":["Marcelo",22,"Masculino"]},{"DATETIME":1714064390065,"ACAO":"LEITURA","DADO":""},{"DATETIME":1714064391865,"ACAO":"DELECAO","DADO":["Dwayne Melendez",35,"Feminino"]},{"DATETIME":1714064431832,"ACAO":"LEITURA","DADO":""},{"DATETIME":1714064433298,"ACAO":"DELECAO","DADO":["Marcelo",22,"Masculino"]},{"DATETIME":1714065084863,"ACAO":"LEITURA","DADO":""},{"DATETIME":1714065086695,"ACAO":"LEITURA","DADO":""},{"DATETIME":1714065148303,"ACAO":"LEITURA","DADO":""},{"DATETIME":1714065149321,"ACAO":"LEITURA","DADO":""},{"DATETIME":1714065198164,"ACAO":"LEITURA","DADO":""},{"DATETIME":1714065200197,"ACAO":"LEITURA","DADO":""},{"DATETIME":1714065214318,"ACAO":"LEITURA","DADO":""},{"DATETIME":1714065215404,"ACAO":"LEITURA","DADO":""},{"DATETIME":1714065331649,"ACAO":"LEITURA","DADO":""},{"DATETIME":1714065332688,"ACAO":"LEITURA","DADO":""},{"DATETIME":1714065412978,"ACAO":"LEITURA","DADO":""},{"DATETIME":1714065413887,"ACAO":"LEITURA","DADO":""},{"DATETIME":1714065441789,"ACAO":"LEITURA","DADO":""},{"DATETIME":1714065443283,"ACAO":"LEITURA","DADO":""},{"DATETIME":1714065511191,"ACAO":"LEITURA","DADO":""},{"DATETIME":1714065511793,"ACAO":"LEITURA","DADO":""},{"DATETIME":1714065577968,"ACAO":"LEITURA","DADO":""},{"DATETIME":1714065578715,"ACAO":"LEITURA","DADO":""},{"DATETIME":1714065635058,"ACAO":"LEITURA","DADO":""},{"DATETIME":1714065635559,"ACAO":"LEITURA","DADO":""},{"DATETIME":1714065742055,"ACAO":"LEITURA","DADO":""},{"DATETIME":1714065743172,"ACAO":"LEITURA","DADO":""},{"DATETIME":1714065861435,"ACAO":"LEITURA","DADO":""},{"DATETIME":1714065902867,"ACAO":"LEITURA","DADO":""},{"DATETIME":1714065929778,"ACAO":"LEITURA","DADO":""},{"DATETIME":1714066024054,"ACAO":"LEITURA","DADO":""},{"DATETIME":1714066024382,"ACAO":"LEITURA","DADO":""},{"DATETIME":1714066046105,"ACAO":"LEITURA","DADO":""},{"DATETIME":1714066046530,"ACAO":"LEITURA","DADO":""},{"DATETIME":1714066110502,"ACAO":"LEITURA","DADO":""},{"DATETIME":1714066112042,"ACAO":"LEITURA","DADO":""},{"DATETIME":1714066112052,"ACAO":"LEITURA","DADO":""},{"DATETIME":1714066216223,"ACAO":"LEITURA","DADO":""},{"DATETIME":1714066216634,"ACAO":"DELECAO","DADO":["Raio-X"]},{"DATETIME":1714066216642,"ACAO":"LEITURA","DADO":""},{"DATETIME":1714066240932,"ACAO":"LEITURA","DADO":""},{"DATETIME":1714066242157,"ACAO":"DELECAO","DADO":["Raio-X"]},{"DATETIME":1714066242165,"ACAO":"LEITURA","DADO":""},{"DATETIME":1714066242174,"ACAO":"LEITURA","DADO":""}]